{
    "@context": [
        "https://raw.githubusercontent.com/iudx/iudx-ld/master/data_models/power/feeder/pwr_feeder_slfeederShree_0.json"
    ],
    "id": "u7734jd399834r8696",
    "NAME": {
        "type": "Property",
        "value": "XYZ"
    },
    "PANEL_ID": {
        "type": "Property",
        "value": "18419"
    },
    "PANEL_NAME": {
        "type": "Property",
        "value": "KN-13"
    },
    "accessInformation": [
        {
            "accessObjectType": "OpenAPI",
            "accessObjectURL": "https://slfeeder.com/APIs",
            "accessObject": {
        "value": "https://raw.githubusercontent.com/iudx/iudx-ld/master/data_models/power/feeder/examples/exApiObject_pwr_feeder_slfeederShree_0.json",
                "type": "Relationship"
            },
            "accessObjectVariables": {
                "type": "Property",
                "value": {
                    "NAME": "XYZ",
                    "ip": "https://pune.iudx.org.in",
                    "port": "443",
                    "resourceClass": "streetlight-feeder-sree"
                }
            }
        }
    ],
    "createdAt": {
        "type": "TimeProperty",
        "value": "2019-02-20T17:30:06.093121"
    },
    "itemDescription": "Streetlight Feeder Item",
    "itemStatus": {
        "type": "Property",
        "value": "active"
    },
    "itemType": {
        "type": "Property",
        "value": "resourceItem"
    },
    "latestResourceData": {
        "type": "Property",
        "value": "https://pune.iudx.org.in/api/1.0.0/resource/latest/streetlight-feeder-sree/XYZ"
    },
    "location": {
        "type": "GeoProperty",
        "value": {
            "geometry": {
                "type": "Point",
                "coordinates": [  73.89856 , 18.4813499]
            }
        }
    },
    "provider": {
        "value": "urn:iudx-cat:ae48f2-5c01e8-3feda9",
        "type": "Relationship"
    },
    "refBaseSchema": {
        "value": "https://raw.githubusercontent.com/iudx/iudx-ld/master/base_schemas/v0.0.0/resourceItem_schema.json",
        "type": "Relationship"
    },
    "refDataModel": {
        "value": "https://raw.githubusercontent.com/iudx/iudx-ld/master/data_models/power/feeder/pwr_feeder_slfeederShree_0.json",
        "type": "Relationship"
    },
    "resourceId": {
        "type": "Property",
        "value": "XYZ"
    },
    "resourceServer": {
        "value": "urn:iudx-cat:636485-945454-2a9495",
        "type": "Relationship"
    },
    "resourceServerGroup": {
        "value": "urn:iudx-cat:abc357-gw2554-12ec83",
        "type": "Relationship"
    },
    "tags": {
        "type": "Property",
        "value": [ "streetlighting", "streetlight", "feeder", "power" ]
    }
}
